setup.py
pep8nazi/__init__.py
pep8nazi.egg-info/PKG-INFO
pep8nazi.egg-info/SOURCES.txt
pep8nazi.egg-info/dependency_links.txt
pep8nazi.egg-info/not-zip-safe
pep8nazi.egg-info/top_level.txt