Metadata-Version: 1.0
Name: pep8nazi
Version: 0.1
Summary: PEP8 Nazi: because really, you have no excuse.
Home-page: http://github.com/storborg/pep8nazi
Author: Scott Torborg
Author-email: storborg@gmail.com
License: MIT
Keywords: pep8
Platform: UNKNOWN
Classifier: License :: OSI Approved :: MIT License
Classifier: Programming Language :: Python :: 2.7
